dp_wizard/VERSION
dp_wizard/__init__.py
dp_wizard/app.py
dp_wizard/types.py
dp_wizard/.local-config/.gitignore
dp_wizard/.local-sessions/.gitignore
dp_wizard/shiny/__init__.py
dp_wizard/shiny/assets/favicon.ico
dp_wizard/shiny/assets/styles.css
dp_wizard/shiny/components/icons.py
dp_wizard/shiny/components/inputs.py
dp_wizard/shiny/components/outputs.py
dp_wizard/shiny/components/summaries.py
dp_wizard/shiny/panels/__init__.py
dp_wizard/shiny/panels/about_panel/__init__.py
dp_wizard/shiny/panels/analysis_panel/__init__.py
dp_wizard/shiny/panels/analysis_panel/column_module.py
dp_wizard/shiny/panels/analysis_panel/group_module.py
dp_wizard/shiny/panels/dataset_panel/__init__.py
dp_wizard/shiny/panels/dataset_panel/data_source.py
dp_wizard/shiny/panels/results_panel/__init__.py
dp_wizard/shiny/panels/results_panel/download_options.py
dp_wizard/shiny/vendor/highlight.js/11.11.1/highlight.min.js
dp_wizard/shiny/vendor/highlight.js/11.11.1/styles/default.min.css
dp_wizard/utils/.gitignore
dp_wizard/utils/argparse_helpers.py
dp_wizard/utils/config.py
dp_wizard/utils/constraints.py
dp_wizard/utils/csv_helper.py
dp_wizard/utils/dp_helper.py
dp_wizard/utils/mock_data.py
dp_wizard/utils/code_generators/__init__.py
dp_wizard/utils/code_generators/abstract_generator.py
dp_wizard/utils/code_generators/notebook_generator.py
dp_wizard/utils/code_generators/script_generator.py
dp_wizard/utils/code_generators/analyses/__init__.py
dp_wizard/utils/code_generators/analyses/histogram/__init__.py
dp_wizard/utils/code_generators/analyses/histogram/no-tests/_histogram_expr.py
dp_wizard/utils/code_generators/analyses/histogram/no-tests/_histogram_notebook_output.py
dp_wizard/utils/code_generators/analyses/histogram/no-tests/_histogram_report_kv.py
dp_wizard/utils/code_generators/analyses/histogram/no-tests/_histogram_script_output.py
dp_wizard/utils/code_generators/analyses/mean/__init__.py
dp_wizard/utils/code_generators/analyses/mean/no-tests/_mean_expr.py
dp_wizard-0.7.0.dist-info/entry_points.txt
dp_wizard-0.7.0.dist-info/licenses/LICENSE
dp_wizard-0.7.0.dist-info/WHEEL
dp_wizard-0.7.0.dist-info/METADATA
dp_wizard-0.7.0.dist-info/RECORD
